Metadata-Version: 1.1
Name: nebulatest2
Version: 11.0.1
Summary: A small example package
Home-page: https://www.msra.cn/zh-cn/news/outreach-articles/%E6%96%B0%E4%B9%A6%E5%8F%91%E5%B8%83%EF%BC%81%E3%80%8A%E6%99%BA%E8%83%BD%E4%B9%8B%E9%97%A8%E3%80%8B%E5%B8%A6%E4%BD%A0%E4%B8%80%E7%AA%A5-ai-%E4%B8%96%E7%95%8C
Author: xiaowuhu
Author-email: hu.xiaowu@hotmail.com
License: MIT License
Platform: all
Classifier: Intended Audience :: Developers
Classifier: Operating System :: OS Independent
Classifier: Natural Language :: Chinese (Simplified)
Classifier: Programming Language :: Python
Classifier: Programming Language :: Python :: 3
Classifier: Programming Language :: Python :: 3.5
Classifier: Programming Language :: Python :: 3.6
Classifier: Programming Language :: Python :: 3.7
Classifier: Programming Language :: Python :: 3.8
Classifier: Topic :: Software Development :: Libraries
